secmmf/__init__.py
secmmf/parser.py
secmmf/secmmf.py
test/__init__.py
secmmf-1.0.2.dist-info/LICENSE
secmmf-1.0.2.dist-info/METADATA
secmmf-1.0.2.dist-info/WHEEL
secmmf-1.0.2.dist-info/top_level.txt
secmmf-1.0.2.dist-info/RECORD
