Metadata-Version: 2.1
Name: secmmf
Version: 1.0.2
Summary: Python scraper for SEC N-MFP2 filings.
Home-page: https://github.com/yj1990/sec_mmf
Author: Yangjue Han
Author-email: yangjue.han20@gmail.com
License: UNKNOWN
Platform: UNKNOWN
Classifier: Programming Language :: Python :: 3
Classifier: License :: OSI Approved :: MIT License
Classifier: Operating System :: OS Independent
Requires-Python: >=3.6
